fds/__init__.py
fds/sdk/__init__.py
fds/sdk/Vermilion/__init__.py
fds/sdk/Vermilion/api_client.py
fds/sdk/Vermilion/configuration.py
fds/sdk/Vermilion/exceptions.py
fds/sdk/Vermilion/model_utils.py
fds/sdk/Vermilion/rest.py
fds/sdk/Vermilion/api/__init__.py
fds/sdk/Vermilion/api/datasource_api.py
fds/sdk/Vermilion/api/entity_api.py
fds/sdk/Vermilion/api/report_api.py
fds/sdk/Vermilion/api/report_instance_api.py
fds/sdk/Vermilion/api/scim_api.py
fds/sdk/Vermilion/api/version_api.py
fds/sdk/Vermilion/api/workflow_api.py
fds/sdk/Vermilion/apis/__init__.py
fds/sdk/Vermilion/model/__init__.py
fds/sdk/Vermilion/model/create_scim_user_json_request.py
fds/sdk/Vermilion/model/create_scim_user_json_request_name.py
fds/sdk/Vermilion/model/created_scim_user_json_response.py
fds/sdk/Vermilion/model/created_scim_user_json_response_meta.py
fds/sdk/Vermilion/model/data_source_all_data.py
fds/sdk/Vermilion/model/data_source_data.py
fds/sdk/Vermilion/model/data_source_data_instance.py
fds/sdk/Vermilion/model/data_source_dto.py
fds/sdk/Vermilion/model/data_source_instance.py
fds/sdk/Vermilion/model/data_source_instance_rows.py
fds/sdk/Vermilion/model/data_source_list.py
fds/sdk/Vermilion/model/data_source_list_meta.py
fds/sdk/Vermilion/model/data_source_list_meta_pagination.py
fds/sdk/Vermilion/model/entity_dto.py
fds/sdk/Vermilion/model/entity_field_value_dto.py
fds/sdk/Vermilion/model/entity_field_value_dto_meta.py
fds/sdk/Vermilion/model/entity_field_value_dto_meta_pagination.py
fds/sdk/Vermilion/model/entity_selection.py
fds/sdk/Vermilion/model/error.py
fds/sdk/Vermilion/model/error_list.py
fds/sdk/Vermilion/model/generate_schedule_response.py
fds/sdk/Vermilion/model/record_set_field_values.py
fds/sdk/Vermilion/model/record_set_fields.py
fds/sdk/Vermilion/model/report_definition_data.py
fds/sdk/Vermilion/model/report_definition_dto.py
fds/sdk/Vermilion/model/report_definition_list.py
fds/sdk/Vermilion/model/report_definition_list_meta.py
fds.sdk.Vermilion-1.3.0.dist-info/LICENSE
fds.sdk.Vermilion-1.3.0.dist-info/METADATA
fds.sdk.Vermilion-1.3.0.dist-info/WHEEL
fds.sdk.Vermilion-1.3.0.dist-info/top_level.txt
fds.sdk.Vermilion-1.3.0.dist-info/RECORD
